cacholong_cli/AsyncTyper.py
cacholong_cli/__init__.py
cacholong_cli/cli.py
cacholong_cli/commands/accounts.py
cacholong_cli/commands/addresses.py
cacholong_cli/commands/companies.py
cacholong_cli/commands/dns_records.py
cacholong_cli/commands/dns_templates.py
cacholong_cli/commands/dns_zones.py
cacholong_cli/commands/products.py
cacholong_cli/commands/purchases.py
cacholong_cli/common.py
cacholong_cli/connection.py
cacholong_sdk/__init__.py
cacholong_sdk/account.py
cacholong_sdk/address.py
cacholong_sdk/api_schema.py
cacholong_sdk/common.py
cacholong_sdk/company.py
cacholong_sdk/connection.py
cacholong_sdk/dns_record.py
cacholong_sdk/dns_template.py
cacholong_sdk/dns_zone.py
cacholong_sdk/exception.py
cacholong_sdk/product.py
cacholong_sdk/purchase.py
jsonapi_client/__init__.py
jsonapi_client/common.py
jsonapi_client/document.py
jsonapi_client/exceptions.py
jsonapi_client/filter.py
jsonapi_client/objects.py
jsonapi_client/relationships.py
jsonapi_client/resourceobject.py
jsonapi_client/session.py
cacholong_cloud_cli-0.3.4.dist-info/METADATA
cacholong_cloud_cli-0.3.4.dist-info/WHEEL
cacholong_cloud_cli-0.3.4.dist-info/entry_points.txt
cacholong_cloud_cli-0.3.4.dist-info/RECORD
