Metadata-Version: 2.3
Name: cacholong-cloud-cli
Version: 0.3.4
Summary: Cacholong CLI, manage cloud environments at Cacholong!
License: MIT
Author: Matthijs Möhlmann
Author-email: matthijs@cacholong.nl
Requires-Python: >=3.11,<4.0
Classifier: License :: OSI Approved :: MIT License
Classifier: Programming Language :: Python :: 3
Classifier: Programming Language :: Python :: 3.11
Classifier: Programming Language :: Python :: 3.12
Classifier: Programming Language :: Python :: 3.13
Requires-Dist: aiodns (>=3.5.0,<4.0.0)
Requires-Dist: aiofiles (>=23.2.1,<24.0.0)
Requires-Dist: aiohttp (>=3.0)
Requires-Dist: jsonschema (>=4.25.1,<5.0.0)
Requires-Dist: pyxdg
Requires-Dist: requests (>=2.32.5,<3.0.0)
Requires-Dist: rich
Requires-Dist: typer
Requires-Dist: types-aiofiles (>=23.2.0.20240403,<24.0.0.0)
